usports_basketball/__init__.py
usports_basketball/constants.py
usports_basketball/player_stats/__init__.py
usports_basketball/player_stats/player_settings.py
usports_basketball/player_stats/data_fetching/__init__.py
usports_basketball/player_stats/data_fetching/fetch_player_stats.py
usports_basketball/player_stats/data_processing/__init__.py
usports_basketball/player_stats/data_processing/players_df.py
usports_basketball/team_stats/__init__.py
usports_basketball/team_stats/team_settings.py
usports_basketball/team_stats/data_fetching/__init__.py
usports_basketball/team_stats/data_fetching/fetch_standings_data.py
usports_basketball/team_stats/data_fetching/fetch_team_stats.py
usports_basketball/team_stats/data_processing/__init__.py
usports_basketball/team_stats/data_processing/standings.py
usports_basketball/team_stats/data_processing/team_stats.py
usports_basketball/utils/__init__.py
usports_basketball/utils/headers.py
usports_basketball/utils/helpers.py
usports_basketball/utils/logging_config.py
usports_basketball-2.0.3.dist-info/LICENSE
usports_basketball-2.0.3.dist-info/METADATA
usports_basketball-2.0.3.dist-info/WHEEL
usports_basketball-2.0.3.dist-info/top_level.txt
usports_basketball-2.0.3.dist-info/RECORD
