Metadata-Version: 2.1
Name: usports-basketball
Version: 2.0.3
Summary: A Python package for current U Sports basketball stats.
Author-email: OJ Adeyemi <ojieadeyemi@gmail.com>
License: MIT License
Project-URL: Repository, https://github.com/ojadeyemi/usports-basketball.git
Project-URL: Issues, https://github.com/ojadeyemi/usports-basketball/issues
Project-URL: Changelog, https://github.com/ojadeyemi/usports-basketball/blob/main/CHANGELOG.md
Keywords: basketball,usports,statistics,data analysis,web scraping,playwright,sports analytics,college basketball,developer tools
Classifier: Development Status :: 5 - Production/Stable
Classifier: License :: OSI Approved :: MIT License
Classifier: Operating System :: OS Independent
Classifier: Intended Audience :: Developers
Classifier: Programming Language :: Python :: 3
Classifier: Programming Language :: Python :: 3 :: Only
Classifier: Programming Language :: Python :: 3.10
Classifier: Programming Language :: Python :: 3.11
Classifier: Programming Language :: Python :: 3.12
Classifier: Programming Language :: Python :: Implementation :: CPython
Requires-Python: >=3.10
License-File: LICENSE
Requires-Dist: beautifulsoup4>=4.12
Requires-Dist: pandas>=2.2
Requires-Dist: playwright>=1.49
Requires-Dist: requests>=2.32
Provides-Extra: dev
Requires-Dist: ruff; extra == "dev"
Provides-Extra: test
Requires-Dist: pytest==8.4; extra == "test"
